Workbook

Sheet 📦 Purchases
A2: Track every item you buy to resell • Blue cells = your input • Formulas auto-calculate
A3: # | B3: Date Bought | C3: Product Name | D3: Category | E3: Qty Bought | F3: Unit Cost ($) | G3: Total Cost ($) | H3: Store / Source | I3: Purchase Method | J3: Item ID / SKU | K3: Condition | L3: Notes
A4: =IF(B4="","",ROW()-3) -> 1 | B4: 46134 | C4: Prismatic Evolution ETB | D4: Pokemon | E4: 3 | F4: 52.99 | G4: =IF(OR(E4="",F4=""),"",E4*F4) -> 158.97 | H4: Bestbuy | I4: Manual | J4: ETB-PE | K4: New
A5: =IF(B5="","",ROW()-3) -> 2 | B5: 46136 | C5: Ascended Heroes BB | D5: Pokemon | E5: 2 | F5: 31.79 | G5: =IF(OR(E5="",F5=""),"",E5*F5) -> 63.58 | H5: Target | I5: ACO | J5: BB-AH | K5: New
A6: =IF(B6="","",ROW()-3) -> 3 | B6: 46137 | C6: Ascended Heroes Ex box | D6: Pokemon | E6: 3 | F6: 20.49 | G6: =IF(OR(E6="",F6=""),"",E6*F6) -> 61.47 | H6: Costco | I6: Manual | J6: EX-AH | K6: New
A7: =IF(B7="","",ROW()-3) -> 4 | B7: 46113 | C7: Ascended Heroes ETB | D7: Pokemon | E7: 1 | F7: 52.99 | G7: 52.99 | H7: Vending | I7: Manual | J7: ETB-AH | K7: New
A8: =IF(B8="","",ROW()-3) -> 5 | B8: 46155 | C8: Chaos Rising PKC ETB | D8: Pokemon | E8: 2 | F8: 59.99 | G8: 119.98 | H8: PKC | I8: ACO | J8: PKCETB-CR | K8: New
A9: =IF(B9="","",ROW()-3) -> 6 | B9: 46155 | C9: Chaos Rising BB | D9: Pokemon | E9: 2 | F9: 26.94 | G9: 53.88 | H9: PKC | I9: ACO | J9: BB-CR | K9: New
A10: =IF(B10="","",ROW()-3) -> 7 | B10: 46155 | C10: Chaos Rising Booster display | D10: Pokemon | E10: 1 | F10: 161.64 | G10: 161.64 | H10: PKC | I10: ACO | J10: BD-CR | K10: New
A11: =IF(B11="","",ROW()-3) -> 8 | B11: 46141 | C11: Ascended heroes poster | D11: Pokemon | E11: 5 | F11: 63.57 | G11: =IF(OR(E11="",F11=""),"",E11*F11) -> 317.85 | H11: Walmart | I11: Refract | J11: PO-AH | K11: New
A12: =IF(B12="","",ROW()-3) -> 9 | B12: 46141 | C12: First Partner illustration | D12: Pokemon | E12: 5 | F12: 19.05 | G12: =IF(OR(E12="",F12=""),"",E12*F12) -> 95.25 | H12: Walmart | I12: Refract | J12: FPI | K12: New
A13: =IF(B13="","",ROW()-3) -> 10 | B13: 46143 | C13: First Partner illustration | D13: Pokemon | E13: 2 | F13: 19.05 | G13: =IF(OR(E13="",F13=""),"",E13*F13) -> 38.1 | H13: Target | I13: Refract | J13: FPI | K13: New
A14: =IF(B14="","",ROW()-3) -> 11 | B14: 46148 | C14: Congratulation Set (W) | D14: Coins | E14: 1 | F14: 180.95 | G14: =IF(OR(E14="",F14=""),"",E14*F14) -> 180.95 | H14: U.S Mint | I14: Manual | J14: CSW | K14: New
A15: =IF(B15="","",ROW()-3) | G15: =IF(OR(E15="",F15=""),"",E15*F15)
A16: =IF(B16="","",ROW()-3) | G16: =IF(OR(E16="",F16=""),"",E16*F16)
A17: =IF(B17="","",ROW()-3) | G17: =IF(OR(E17="",F17=""),"",E17*F17)
A18: =IF(B18="","",ROW()-3) | G18: =IF(OR(E18="",F18=""),"",E18*F18)
A19: =IF(B19="","",ROW()-3) | G19: =IF(OR(E19="",F19=""),"",E19*F19)
A20: =IF(B20="","",ROW()-3) | G20: =IF(OR(E20="",F20=""),"",E20*F20)
A21: =IF(B21="","",ROW()-3) | G21: =IF(OR(E21="",F21=""),"",E21*F21)
A22: =IF(B22="","",ROW()-3) | G22: =IF(OR(E22="",F22=""),"",E22*F22)
A23: =IF(B23="","",ROW()-3) | G23: =IF(OR(E23="",F23=""),"",E23*F23)
A24: =IF(B24="","",ROW()-3) | G24: =IF(OR(E24="",F24=""),"",E24*F24)
A25: =IF(B25="","",ROW()-3) | G25: =IF(OR(E25="",F25=""),"",E25*F25)
A26: =IF(B26="","",ROW()-3) | G26: =IF(OR(E26="",F26=""),"",E26*F26)
... A78: =IF(B78="","",ROW()-3) | G78: =IF(OR(E78="",F78=""),"",E78*F78)
A79: TOTAL PURCHASE COST | G79: =SUM(G4:G78) -> 1304.66
A81: 💡 LEGEND: Blue text = your input | Black text = auto-calculated | Purchase Methods: Cash · Card · PayPal · Venmo · Zelle · Check · Other

Sheet 💵 Sales
A1: w
A2: Track every item you sell • Blue cells = your input • Profit columns auto-calculate from Purchase Log
A3: # | B3: Date Sold | C3: Product Name | D3: Item ID / SKU | E3: Qty Sold | F3: Sale Price/Unit ($) | G3: Gross Revenue ($) | H3: Sold On / Platform | I3: Sale Method | J3: Unit Cost ($) | K3: Total Cost ($) | L3: Net Profit ($) | M3: Margin %
A4: =IF(B4="","",ROW()-3) -> 1 | B4: 46137 | C4: Prismatic Evolution ETB | D4: ETB-PE | E4: 3 | F4: 153.33 | G4: =IF(OR(E4="",F4=""),"",E4*F4) -> 459.99 | H4: Marketplace | I4: Zelle | J4: 52.99 | K4: =IF(OR(E4="",J4=""),"",E4*J4) -> 158.97 | L4: =IF(OR(G4="",K4=""),"",G4-K4) -> 301.02 | M4: =IFERROR(IF(G4="","",L4/G4),"") -> 0.65440553
A5: =IF(B5="","",ROW()-3) -> 2 | B5: 46117 | C5: Ascended Heroes ETB | D5: EX-AH | E5: 1 | F5: 110 | G5: =IF(OR(E5="",F5=""),"",E5*F5) -> 110 | H5: Marketplace | I5: Zelle | J5: 52.99 | K5: =IF(OR(E5="",J5=""),"",E5*J5) -> 52.99 | L5: =IF(OR(G5="",K5=""),"",G5-K5) -> 57.01 | M5: =IFERROR(IF(G5="","",L5/G5),"") -> 0.51827273
A6: =IF(B6="","",ROW()-3) -> 3 | B6: 46145 | C6: First Partner illustration | D6: FPI | E6: 5 | F6: 42.8 | G6: =IF(OR(E6="",F6=""),"",E6*F6) -> 214 | H6: Tradepost | I6: Direct Deposit | J6: 19.05 | K6: =IF(OR(E6="",J6=""),"",E6*J6) -> 95.25 | L6: =IF(OR(G6="",K6=""),"",G6-K6) -> 118.75 | M6: =IFERROR(IF(G6="","",L6/G6),"") -> 0.55490654
A7: =IF(B7="","",ROW()-3) -> 4 | B7: 46150 | C7: AH booster packs | D7: AH-BP | E7: 59 | F7: 11.73 | G7: =IF(OR(E7="",F7=""),"",E7*F7) -> 692.07 | H7: Tradepost | I7: Direct Deposit | J7: 6.43 | K7: =IF(OR(E7="",J7=""),"",E7*J7) -> 379.37 | L7: =IF(OR(G7="",K7=""),"",G7-K7) -> 312.7 | M7: =IFERROR(IF(G7="","",L7/G7),"") -> 0.45183291
A8: =IF(B8="","",ROW()-3) -> 5 | B8: 46155 | C8: Ascended Heroes BB | D8: AH-BB | E8: 2 | F8: 72.5 | G8: =IF(OR(E8="",F8=""),"",E8*F8) -> 145 | H8: Marketplace | I8: Zelle | J8: 31.79 | K8: =IF(OR(E8="",J8=""),"",E8*J8) -> 63.58 | L8: =IF(OR(G8="",K8=""),"",G8-K8) -> 81.42 | M8: =IFERROR(IF(G8="","",L8/G8),"") -> 0.56151724
A9: =IF(B9="","",ROW()-3) | G9: =IF(OR(E9="",F9=""),"",E9*F9) | K9: =IF(OR(E9="",J9=""),"",E9*J9) | L9: =IF(OR(G9="",K9=""),"",G9-K9) | M9: =IFERROR(IF(G9="","",L9/G9),"")
A10: =IF(B10="","",ROW()-3) | G10: =IF(OR(E10="",F10=""),"",E10*F10) | K10: =IF(OR(E10="",J10=""),"",E10*J10) | L10: =IF(OR(G10="",K10=""),"",G10-K10) | M10: =IFERROR(IF(G10="","",L10/G10),"")
A11: =IF(B11="","",ROW()-3) | G11: =IF(OR(E11="",F11=""),"",E11*F11) | K11: =IF(OR(E11="",J11=""),"",E11*J11) | L11: =IF(OR(G11="",K11=""),"",G11-K11) | M11: =IFERROR(IF(G11="","",L11/G11),"")
A12: =IF(B12="","",ROW()-3) | G12: =IF(OR(E12="",F12=""),"",E12*F12) | K12: =IF(OR(E12="",J12=""),"",E12*J12) | L12: =IF(OR(G12="",K12=""),"",G12-K12) | M12: =IFERROR(IF(G12="","",L12/G12),"")
A13: =IF(B13="","",ROW()-3) | G13: =IF(OR(E13="",F13=""),"",E13*F13) | K13: =IF(OR(E13="",J13=""),"",E13*J13) | L13: =IF(OR(G13="",K13=""),"",G13-K13) | M13: =IFERROR(IF(G13="","",L13/G13),"")
A14: =IF(B14="","",ROW()-3) | G14: =IF(OR(E14="",F14=""),"",E14*F14) | K14: =IF(OR(E14="",J14=""),"",E14*J14) | L14: =IF(OR(G14="",K14=""),"",G14-K14) | M14: =IFERROR(IF(G14="","",L14/G14),"")
A15: =IF(B15="","",ROW()-3) | G15: =IF(OR(E15="",F15=""),"",E15*F15) | K15: =IF(OR(E15="",J15=""),"",E15*J15) | L15: =IF(OR(G15="",K15=""),"",G15-K15) | M15: =IFERROR(IF(G15="","",L15/G15),"")
A16: =IF(B16="","",ROW()-3) | G16: =IF(OR(E16="",F16=""),"",E16*F16) | K16: =IF(OR(E16="",J16=""),"",E16*J16) | L16: =IF(OR(G16="",K16=""),"",G16-K16) | M16: =IFERROR(IF(G16="","",L16/G16),"")
A17: =IF(B17="","",ROW()-3) | G17: =IF(OR(E17="",F17=""),"",E17*F17) | K17: =IF(OR(E17="",J17=""),"",E17*J17) | L17: =IF(OR(G17="",K17=""),"",G17-K17) | M17: =IFERROR(IF(G17="","",L17/G17),"")
A18: =IF(B18="","",ROW()-3) | G18: =IF(OR(E18="",F18=""),"",E18*F18) | K18: =IF(OR(E18="",J18=""),"",E18*J18) | L18: =IF(OR(G18="",K18=""),"",G18-K18) | M18: =IFERROR(IF(G18="","",L18/G18),"")
A19: =IF(B19="","",ROW()-3) | G19: =IF(OR(E19="",F19=""),"",E19*F19) | K19: =IF(OR(E19="",J19=""),"",E19*J19) | L19: =IF(OR(G19="",K19=""),"",G19-K19) | M19: =IFERROR(IF(G19="","",L19/G19),"")
A20: =IF(B20="","",ROW()-3) | G20: =IF(OR(E20="",F20=""),"",E20*F20) | K20: =IF(OR(E20="",J20=""),"",E20*J20) | L20: =IF(OR(G20="",K20=""),"",G20-K20) | M20: =IFERROR(IF(G20="","",L20/G20),"")
... A78: =IF(B78="","",ROW()-3) | G78: =IF(OR(E78="",F78=""),"",E78*F78) | K78: =IF(OR(E78="",J78=""),"",E78*J78) | L78: =IF(OR(G78="",K78=""),"",G78-K78) | M78: =IFERROR(IF(G78="","",L78/G78),"")
A79: TOTALS | G79: =SUM(G4:G78) -> 1621.06 | K79: =SUM(K4:K78) -> 750.16 | L79: =SUM(L4:L78) -> 870.9 | M79: =IFERROR(L79/G79,"") -> 0.53724106
A81: 💡 Platforms: eBay · Facebook Marketplace · Mercari · OfferUp · Poshmark · Depop · Amazon · Etsy · In-Person · Other | Sale Methods: Cash · Card · PayPal · Venmo · Zelle

Sheet 📋 Inventory
A1: 📋 INVENTORY TRACKER — What You Still Have
A2: Track unsold inventory • Enter Item ID to link back to Purchase Log
A3: # | B3: Item ID / SKU | C3: Product Name | D3: Category | E3: Qty in Stock | F3: Unit Cost ($) | G3: Value in Stock ($) | H3: Listed? | I3: Notes
A4: =IF(B4="","",ROW()-3) -> 1 | B4: BB-AH | C4: Ascended Heroes BB | D4: Pokemon | E4: 2 | F4: 70 | G4: =IF(OR(E4="",F4=""),"",E4*F4) -> 140 | H4: No
A5: =IF(B5="","",ROW()-3) -> 2 | B5: EX-AH | C5: Ascended Heroes Ex box | D5: Pokemon | E5: 3 | F5: 50 | G5: =IF(OR(E5="",F5=""),"",E5*F5) -> 150 | H5: No | I5: BROKE DOWN
A6: =IF(B6="","",ROW()-3) -> 3 | B6: PKCETB-CR | C6: Chaos Rising PKC ETB | D6: Pokemon | E6: 2 | G6: =IF(OR(E6="",F6=""),"",E6*F6) | H6: No
A7: =IF(B7="","",ROW()-3) -> 4 | B7: BB-CR | C7: Chaos Rising BB | D7: Pokemon | E7: 2 | G7: =IF(OR(E7="",F7=""),"",E7*F7) | H7: No
A8: =IF(B8="","",ROW()-3) -> 5 | B8: BD-CR | C8: Chaos Rising booster display | D8: Pokemon | E8: 1 | G8: =IF(OR(E8="",F8=""),"",E8*F8) | H8: No
A9: =IF(B9="","",ROW()-3) -> 6 | B9: PO-AH | C9: Ascended heroes poster | D9: Pokemon | E9: 5 | G9: =IF(OR(E9="",F9=""),"",E9*F9) | I9: BROKE DOWN
A10: =IF(B10="","",ROW()-3) -> 7 | B10: FPI | C10: First Partner illustration | D10: Pokemon | E10: 2 | F10: 42.5 | G10: =IF(OR(E10="",F10=""),"",E10*F10) -> 85 | H10: Yes | I10: 5 sold 05/03/2026
A11: =IF(B11="","",ROW()-3) | G11: =IF(OR(E11="",F11=""),"",E11*F11)
A12: =IF(B12="","",ROW()-3) | G12: =IF(OR(E12="",F12=""),"",E12*F12)
A13: =IF(B13="","",ROW()-3) | G13: =IF(OR(E13="",F13=""),"",E13*F13)
A14: =IF(B14="","",ROW()-3) | G14: =IF(OR(E14="",F14=""),"",E14*F14)
A15: =IF(B15="","",ROW()-3) | G15: =IF(OR(E15="",F15=""),"",E15*F15)
A16: =IF(B16="","",ROW()-3) | G16: =IF(OR(E16="",F16=""),"",E16*F16)
A17: =IF(B17="","",ROW()-3) | G17: =IF(OR(E17="",F17=""),"",E17*F17)
A18: =IF(B18="","",ROW()-3) | G18: =IF(OR(E18="",F18=""),"",E18*F18)
A19: =IF(B19="","",ROW()-3) | G19: =IF(OR(E19="",F19=""),"",E19*F19)
A20: =IF(B20="","",ROW()-3) | G20: =IF(OR(E20="",F20=""),"",E20*F20)
A21: =IF(B21="","",ROW()-3) | G21: =IF(OR(E21="",F21=""),"",E21*F21)
A22: =IF(B22="","",ROW()-3) | G22: =IF(OR(E22="",F22=""),"",E22*F22)
... A78: =IF(B78="","",ROW()-3) | G78: =IF(OR(E78="",F78=""),"",E78*F78)
A79: TOTAL INVENTORY VALUE | G79: =SUM(G4:G78) -> 375

Sheet 📊 Dashboard
A1: 📊 RESELLER DASHBOARD — Your Business At a Glance
A3: 💰 REVENUE & COST SUMMARY
A4: Total Gross Revenue (All Sales) | B4: ='💵 Sales'!G79 -> 1621.06
A5: Total Purchase Cost (All Buys) | B5: ='📦 Purchases'!G79 -> 1304.66
A6: Total COGS (from Sales Log) | B6: ='💵 Sales'!K79 -> 750.16
A8: 📈 PROFIT SUMMARY
A9: Gross Profit (Revenue − COGS) | B9: ='💵 Sales'!G79-'💵 Sales'!K79 -> 870.9
A10: Net Profit (After All Costs) | B10: ='💵 Sales'!L79 -> 870.9
A11: Average Profit Margin % | B11: ='💵 Sales'!M79 -> 0.53724106
A12: ROI (Net Profit ÷ Purchase Cost) | B12: =IFERROR('💵 Sales'!L79/'📦 Purchases'!G79,"") -> 0.66753024
A14: 📋 INVENTORY SNAPSHOT
A15: Current Inventory Value | B15: ='📋 Inventory'!G79 -> 375
A16: Total Items Purchased | B16: =SUMIF('📦 Purchases'!B4:B78,"<>",'📦 Purchases'!E4:E78) -> 27
A17: Total Items Sold | B17: =SUMIF('💵 Sales'!B4:B78,"<>",'💵 Sales'!E4:E78) -> 70
A19: 💸 OVERHEAD EXPENSES
A20: Total Overhead Expenses | B20: ='💸 Overhead Expenses'!E79 -> 503.02
A21: True Net (Profit - Overhead) | B21: ='💵 Sales'!L79-'💸 Overhead Expenses'!E79 -> 367.88
A23: 💡 HOW TO USE THIS TRACKER
A24: 📦 Purchases sheet | B24: Log every item you buy: date, product, qty, unit cost, store & payment method
A25: 💵 Sales sheet | B25: Log every sale: date sold, product, qty, sale price, platform & payment method
A26: 📋 Inventory sheet | B26: Track unsold stock — update qty as items sell
A27: 💸 Overhead Expenses | B27: Log non-product costs: fees, supplies, storage, ads, subscriptions, etc.
A28: 📅 Monthly Breakdown | B28: See revenue, profit & overhead broken out by month with a year filter
A29: 📊 Dashboard | B29: All totals auto-calculate — no manual entry needed here
A30: Item ID / SKU | B30: Use a consistent ID (e.g. SHOES-001) across all sheets to link records

Sheet 📅 Monthly Breakdown
A2: Auto-calculated from Sales Log • All figures pull live from 💵 Sales sheet
A3: Year Filter: | D3: ← Type a year (e.g. 2025) to filter by year, or leave blank for all years
A4: Metric | B4: Jan | C4: Feb | D4: Mar | E4: Apr | F4: May | G4: Jun | H4: Jul | I4: Aug | J4: Sep | K4: Oct | L4: Nov | M4: Dec | N4: ANNUAL TOTAL
A5: 💰 Gross Revenue ($) | B5: =IFERROR(SUMPRODUCT((TEXT('💵 Sales'!$B$4:$B$78,"mmm")="Jan")*IF($C$3="",1,('💵 Sales'!$B$4:$B$78<>"")*(YEAR('💵 Sales'!$B$4:$B$78)=$C$3))*IF('💵 Sales'!$G$4:$G$78="",0,'💵 Sales'!$G$4:$G$78)),0) -> 0 | C5: =IFERROR(SUMPRODUCT((TEXT('💵 Sales'!$B$4:$B$78,"mmm")="Feb")*IF($C$3="",1,('💵 Sales'!$B$4:$B$78<>"")*(YEAR('💵 Sales'!$B$4:$B$78)=$C$3))*IF('💵 Sales'!$G$4:$G$78="",0,'💵 Sales'!$G$4:$G$78)),0) -> 0 | D5: =IFERROR(SUMPRODUCT((TEXT('💵 Sales'!$B$4:$B$78,"mmm")="Mar")*IF($C$3="",1,('💵 Sales'!$B$4:$B$78<>"")*(YEAR('💵 Sales'!$B$4:$B$78)=$C$3))*IF('💵 Sales'!$G$4:$G$78="",0,'💵 Sales'!$G$4:$G$78)),0) -> 0 | E5: =IFERROR(SUMPRODUCT((TEXT('💵 Sales'!$B$4:$B$78,"mmm")="Apr")*IF($C$3="",1,('💵 Sales'!$B$4:$B$78<>"")*(YEAR('💵 Sales'!$B$4:$B$78)=$C$3))*IF('💵 Sales'!$G$4:$G$78="",0,'💵 Sales'!$G$4:$G$78)),0) -> 569.99 | F5: =IFERROR(SUMPRODUCT((TEXT('💵 Sales'!$B$4:$B$78,"mmm")="May")*IF($C$3="",1,('💵 Sales'!$B$4:$B$78<>"")*(YEAR('💵 Sales'!$B$4:$B$78)=$C$3))*IF('💵 Sales'!$G$4:$G$78="",0,'💵 Sales'!$G$4:$G$78)),0) -> 1051.07 | G5: =IFERROR(SUMPRODUCT((TEXT('💵 Sales'!$B$4:$B$78,"mmm")="Jun")*IF($C$3="",1,('💵 Sales'!$B$4:$B$78<>"")*(YEAR('💵 Sales'!$B$4:$B$78)=$C$3))*IF('💵 Sales'!$G$4:$G$78="",0,'💵 Sales'!$G$4:$G$78)),0) -> 0 | H5: =IFERROR(SUMPRODUCT((TEXT('💵 Sales'!$B$4:$B$78,"mmm")="Jul")*IF($C$3="",1,('💵 Sales'!$B$4:$B$78<>"")*(YEAR('💵 Sales'!$B$4:$B$78)=$C$3))*IF('💵 Sales'!$G$4:$G$78="",0,'💵 Sales'!$G$4:$G$78)),0) -> 0 | I5: =IFERROR(SUMPRODUCT((TEXT('💵 Sales'!$B$4:$B$78,"mmm")="Aug")*IF($C$3="",1,('💵 Sales'!$B$4:$B$78<>"")*(YEAR('💵 Sales'!$B$4:$B$78)=$C$3))*IF('💵 Sales'!$G$4:$G$78="",0,'💵 Sales'!$G$4:$G$78)),0) -> 0 | J5: =IFERROR(SUMPRODUCT((TEXT('💵 Sales'!$B$4:$B$78,"mmm")="Sep")*IF($C$3="",1,('💵 Sales'!$B$4:$B$78<>"")*(YEAR('💵 Sales'!$B$4:$B$78)=$C$3))*IF('💵 Sales'!$G$4:$G$78="",0,'💵 Sales'!$G$4:$G$78)),0) -> 0 | K5: =IFERROR(SUMPRODUCT((TEXT('💵 Sales'!$B$4:$B$78,"mmm")="Oct")*IF($C$3="",1,('💵 Sales'!$B$4:$B$78<>"")*(YEAR('💵 Sales'!$B$4:$B$78)=$C$3))*IF('💵 Sales'!$G$4:$G$78="",0,'💵 Sales'!$G$4:$G$78)),0) -> 0 | L5: =IFERROR(SUMPRODUCT((TEXT('💵 Sales'!$B$4:$B$78,"mmm")="Nov")*IF($C$3="",1,('💵 Sales'!$B$4:$B$78<>"")*(YEAR('💵 Sales'!$B$4:$B$78)=$C$3))*IF('💵 Sales'!$G$4:$G$78="",0,'💵 Sales'!$G$4:$G$78)),0) -> 0 | M5: =IFERROR(SUMPRODUCT((TEXT('💵 Sales'!$B$4:$B$78,"mmm")="Dec")*IF($C$3="",1,('💵 Sales'!$B$4:$B$78<>"")*(YEAR('💵 Sales'!$B$4:$B$78)=$C$3))*IF('💵 Sales'!$G$4:$G$78="",0,'💵 Sales'!$G$4:$G$78)),0) -> 0 | N5: =SUM(B5:M5) -> 1621.06
A6: 🏭 Total Cost ($) | B6: =IFERROR(SUMPRODUCT((TEXT('💵 Sales'!$B$4:$B$78,"mmm")="Jan")*IF($C$3="",1,('💵 Sales'!$B$4:$B$78<>"")*(YEAR('💵 Sales'!$B$4:$B$78)=$C$3))*IF('💵 Sales'!$K$4:$K$78="",0,'💵 Sales'!$K$4:$K$78)),0) -> 0 | C6: =IFERROR(SUMPRODUCT((TEXT('💵 Sales'!$B$4:$B$78,"mmm")="Feb")*IF($C$3="",1,('💵 Sales'!$B$4:$B$78<>"")*(YEAR('💵 Sales'!$B$4:$B$78)=$C$3))*IF('💵 Sales'!$K$4:$K$78="",0,'💵 Sales'!$K$4:$K$78)),0) -> 0 | D6: =IFERROR(SUMPRODUCT((TEXT('💵 Sales'!$B$4:$B$78,"mmm")="Mar")*IF($C$3="",1,('💵 Sales'!$B$4:$B$78<>"")*(YEAR('💵 Sales'!$B$4:$B$78)=$C$3))*IF('💵 Sales'!$K$4:$K$78="",0,'💵 Sales'!$K$4:$K$78)),0) -> 0 | E6: =IFERROR(SUMPRODUCT((TEXT('💵 Sales'!$B$4:$B$78,"mmm")="Apr")*IF($C$3="",1,('💵 Sales'!$B$4:$B$78<>"")*(YEAR('💵 Sales'!$B$4:$B$78)=$C$3))*IF('💵 Sales'!$K$4:$K$78="",0,'💵 Sales'!$K$4:$K$78)),0) -> 211.96 | F6: =IFERROR(SUMPRODUCT((TEXT('💵 Sales'!$B$4:$B$78,"mmm")="May")*IF($C$3="",1,('💵 Sales'!$B$4:$B$78<>"")*(YEAR('💵 Sales'!$B$4:$B$78)=$C$3))*IF('💵 Sales'!$K$4:$K$78="",0,'💵 Sales'!$K$4:$K$78)),0) -> 538.2 | G6: =IFERROR(SUMPRODUCT((TEXT('💵 Sales'!$B$4:$B$78,"mmm")="Jun")*IF($C$3="",1,('💵 Sales'!$B$4:$B$78<>"")*(YEAR('💵 Sales'!$B$4:$B$78)=$C$3))*IF('💵 Sales'!$K$4:$K$78="",0,'💵 Sales'!$K$4:$K$78)),0) -> 0 | H6: =IFERROR(SUMPRODUCT((TEXT('💵 Sales'!$B$4:$B$78,"mmm")="Jul")*IF($C$3="",1,('💵 Sales'!$B$4:$B$78<>"")*(YEAR('💵 Sales'!$B$4:$B$78)=$C$3))*IF('💵 Sales'!$K$4:$K$78="",0,'💵 Sales'!$K$4:$K$78)),0) -> 0 | I6: =IFERROR(SUMPRODUCT((TEXT('💵 Sales'!$B$4:$B$78,"mmm")="Aug")*IF($C$3="",1,('💵 Sales'!$B$4:$B$78<>"")*(YEAR('💵 Sales'!$B$4:$B$78)=$C$3))*IF('💵 Sales'!$K$4:$K$78="",0,'💵 Sales'!$K$4:$K$78)),0) -> 0 | J6: =IFERROR(SUMPRODUCT((TEXT('💵 Sales'!$B$4:$B$78,"mmm")="Sep")*IF($C$3="",1,('💵 Sales'!$B$4:$B$78<>"")*(YEAR('💵 Sales'!$B$4:$B$78)=$C$3))*IF('💵 Sales'!$K$4:$K$78="",0,'💵 Sales'!$K$4:$K$78)),0) -> 0 | K6: =IFERROR(SUMPRODUCT((TEXT('💵 Sales'!$B$4:$B$78,"mmm")="Oct")*IF($C$3="",1,('💵 Sales'!$B$4:$B$78<>"")*(YEAR('💵 Sales'!$B$4:$B$78)=$C$3))*IF('💵 Sales'!$K$4:$K$78="",0,'💵 Sales'!$K$4:$K$78)),0) -> 0 | L6: =IFERROR(SUMPRODUCT((TEXT('💵 Sales'!$B$4:$B$78,"mmm")="Nov")*IF($C$3="",1,('💵 Sales'!$B$4:$B$78<>"")*(YEAR('💵 Sales'!$B$4:$B$78)=$C$3))*IF('💵 Sales'!$K$4:$K$78="",0,'💵 Sales'!$K$4:$K$78)),0) -> 0 | M6: =IFERROR(SUMPRODUCT((TEXT('💵 Sales'!$B$4:$B$78,"mmm")="Dec")*IF($C$3="",1,('💵 Sales'!$B$4:$B$78<>"")*(YEAR('💵 Sales'!$B$4:$B$78)=$C$3))*IF('💵 Sales'!$K$4:$K$78="",0,'💵 Sales'!$K$4:$K$78)),0) -> 0 | N6: =SUM(B6:M6) -> 750.16
A7: 📈 Net Profit ($) | B7: =IFERROR(SUMPRODUCT((TEXT('💵 Sales'!$B$4:$B$78,"mmm")="Jan")*IF($C$3="",1,('💵 Sales'!$B$4:$B$78<>"")*(YEAR('💵 Sales'!$B$4:$B$78)=$C$3))*IF('💵 Sales'!$L$4:$L$78="",0,'💵 Sales'!$L$4:$L$78)),0) -> 0 | C7: =IFERROR(SUMPRODUCT((TEXT('💵 Sales'!$B$4:$B$78,"mmm")="Feb")*IF($C$3="",1,('💵 Sales'!$B$4:$B$78<>"")*(YEAR('💵 Sales'!$B$4:$B$78)=$C$3))*IF('💵 Sales'!$L$4:$L$78="",0,'💵 Sales'!$L$4:$L$78)),0) -> 0 | D7: =IFERROR(SUMPRODUCT((TEXT('💵 Sales'!$B$4:$B$78,"mmm")="Mar")*IF($C$3="",1,('💵 Sales'!$B$4:$B$78<>"")*(YEAR('💵 Sales'!$B$4:$B$78)=$C$3))*IF('💵 Sales'!$L$4:$L$78="",0,'💵 Sales'!$L$4:$L$78)),0) -> 0 | E7: =IFERROR(SUMPRODUCT((TEXT('💵 Sales'!$B$4:$B$78,"mmm")="Apr")*IF($C$3="",1,('💵 Sales'!$B$4:$B$78<>"")*(YEAR('💵 Sales'!$B$4:$B$78)=$C$3))*IF('💵 Sales'!$L$4:$L$78="",0,'💵 Sales'!$L$4:$L$78)),0) -> 358.03 | F7: =IFERROR(SUMPRODUCT((TEXT('💵 Sales'!$B$4:$B$78,"mmm")="May")*IF($C$3="",1,('💵 Sales'!$B$4:$B$78<>"")*(YEAR('💵 Sales'!$B$4:$B$78)=$C$3))*IF('💵 Sales'!$L$4:$L$78="",0,'💵 Sales'!$L$4:$L$78)),0) -> 512.87 | G7: =IFERROR(SUMPRODUCT((TEXT('💵 Sales'!$B$4:$B$78,"mmm")="Jun")*IF($C$3="",1,('💵 Sales'!$B$4:$B$78<>"")*(YEAR('💵 Sales'!$B$4:$B$78)=$C$3))*IF('💵 Sales'!$L$4:$L$78="",0,'💵 Sales'!$L$4:$L$78)),0) -> 0 | H7: =IFERROR(SUMPRODUCT((TEXT('💵 Sales'!$B$4:$B$78,"mmm")="Jul")*IF($C$3="",1,('💵 Sales'!$B$4:$B$78<>"")*(YEAR('💵 Sales'!$B$4:$B$78)=$C$3))*IF('💵 Sales'!$L$4:$L$78="",0,'💵 Sales'!$L$4:$L$78)),0) -> 0 | I7: =IFERROR(SUMPRODUCT((TEXT('💵 Sales'!$B$4:$B$78,"mmm")="Aug")*IF($C$3="",1,('💵 Sales'!$B$4:$B$78<>"")*(YEAR('💵 Sales'!$B$4:$B$78)=$C$3))*IF('💵 Sales'!$L$4:$L$78="",0,'💵 Sales'!$L$4:$L$78)),0) -> 0 | J7: =IFERROR(SUMPRODUCT((TEXT('💵 Sales'!$B$4:$B$78,"mmm")="Sep")*IF($C$3="",1,('💵 Sales'!$B$4:$B$78<>"")*(YEAR('💵 Sales'!$B$4:$B$78)=$C$3))*IF('💵 Sales'!$L$4:$L$78="",0,'💵 Sales'!$L$4:$L$78)),0) -> 0 | K7: =IFERROR(SUMPRODUCT((TEXT('💵 Sales'!$B$4:$B$78,"mmm")="Oct")*IF($C$3="",1,('💵 Sales'!$B$4:$B$78<>"")*(YEAR('💵 Sales'!$B$4:$B$78)=$C$3))*IF('💵 Sales'!$L$4:$L$78="",0,'💵 Sales'!$L$4:$L$78)),0) -> 0 | L7: =IFERROR(SUMPRODUCT((TEXT('💵 Sales'!$B$4:$B$78,"mmm")="Nov")*IF($C$3="",1,('💵 Sales'!$B$4:$B$78<>"")*(YEAR('💵 Sales'!$B$4:$B$78)=$C$3))*IF('💵 Sales'!$L$4:$L$78="",0,'💵 Sales'!$L$4:$L$78)),0) -> 0 | M7: =IFERROR(SUMPRODUCT((TEXT('💵 Sales'!$B$4:$B$78,"mmm")="Dec")*IF($C$3="",1,('💵 Sales'!$B$4:$B$78<>"")*(YEAR('💵 Sales'!$B$4:$B$78)=$C$3))*IF('💵 Sales'!$L$4:$L$78="",0,'💵 Sales'!$L$4:$L$78)),0) -> 0 | N7: =SUM(B7:M7) -> 870.9
A8: 📐 Profit Margin % | B8: =IFERROR((B5-B6)/B5,0) -> 0 | C8: =IFERROR((C5-C6)/C5,0) -> 0 | D8: =IFERROR((D5-D6)/D5,0) -> 0 | E8: =IFERROR((E5-E6)/E5,0) -> 0.62813383 | F8: =IFERROR((F5-F6)/F5,0) -> 0.48795037 | G8: =IFERROR((G5-G6)/G5,0) -> 0 | H8: =IFERROR((H5-H6)/H5,0) -> 0 | I8: =IFERROR((I5-I6)/I5,0) -> 0 | ... N8: =IFERROR((N5-N6)/N5,0) -> 0.53724106
A9: 📦 Units Sold | B9: =IFERROR(SUMPRODUCT((TEXT('💵 Sales'!$B$4:$B$78,"mmm")="Jan")*IF($C$3="",1,('💵 Sales'!$B$4:$B$78<>"")*(YEAR('💵 Sales'!$B$4:$B$78)=$C$3))*IF('💵 Sales'!$E$4:$E$78="",0,'💵 Sales'!$E$4:$E$78)),0) -> 0 | C9: =IFERROR(SUMPRODUCT((TEXT('💵 Sales'!$B$4:$B$78,"mmm")="Feb")*IF($C$3="",1,('💵 Sales'!$B$4:$B$78<>"")*(YEAR('💵 Sales'!$B$4:$B$78)=$C$3))*IF('💵 Sales'!$E$4:$E$78="",0,'💵 Sales'!$E$4:$E$78)),0) -> 0 | D9: =IFERROR(SUMPRODUCT((TEXT('💵 Sales'!$B$4:$B$78,"mmm")="Mar")*IF($C$3="",1,('💵 Sales'!$B$4:$B$78<>"")*(YEAR('💵 Sales'!$B$4:$B$78)=$C$3))*IF('💵 Sales'!$E$4:$E$78="",0,'💵 Sales'!$E$4:$E$78)),0) -> 0 | E9: =IFERROR(SUMPRODUCT((TEXT('💵 Sales'!$B$4:$B$78,"mmm")="Apr")*IF($C$3="",1,('💵 Sales'!$B$4:$B$78<>"")*(YEAR('💵 Sales'!$B$4:$B$78)=$C$3))*IF('💵 Sales'!$E$4:$E$78="",0,'💵 Sales'!$E$4:$E$78)),0) -> 4 | F9: =IFERROR(SUMPRODUCT((TEXT('💵 Sales'!$B$4:$B$78,"mmm")="May")*IF($C$3="",1,('💵 Sales'!$B$4:$B$78<>"")*(YEAR('💵 Sales'!$B$4:$B$78)=$C$3))*IF('💵 Sales'!$E$4:$E$78="",0,'💵 Sales'!$E$4:$E$78)),0) -> 66 | G9: =IFERROR(SUMPRODUCT((TEXT('💵 Sales'!$B$4:$B$78,"mmm")="Jun")*IF($C$3="",1,('💵 Sales'!$B$4:$B$78<>"")*(YEAR('💵 Sales'!$B$4:$B$78)=$C$3))*IF('💵 Sales'!$E$4:$E$78="",0,'💵 Sales'!$E$4:$E$78)),0) -> 0 | H9: =IFERROR(SUMPRODUCT((TEXT('💵 Sales'!$B$4:$B$78,"mmm")="Jul")*IF($C$3="",1,('💵 Sales'!$B$4:$B$78<>"")*(YEAR('💵 Sales'!$B$4:$B$78)=$C$3))*IF('💵 Sales'!$E$4:$E$78="",0,'💵 Sales'!$E$4:$E$78)),0) -> 0 | I9: =IFERROR(SUMPRODUCT((TEXT('💵 Sales'!$B$4:$B$78,"mmm")="Aug")*IF($C$3="",1,('💵 Sales'!$B$4:$B$78<>"")*(YEAR('💵 Sales'!$B$4:$B$78)=$C$3))*IF('💵 Sales'!$E$4:$E$78="",0,'💵 Sales'!$E$4:$E$78)),0) -> 0 | J9: =IFERROR(SUMPRODUCT((TEXT('💵 Sales'!$B$4:$B$78,"mmm")="Sep")*IF($C$3="",1,('💵 Sales'!$B$4:$B$78<>"")*(YEAR('💵 Sales'!$B$4:$B$78)=$C$3))*IF('💵 Sales'!$E$4:$E$78="",0,'💵 Sales'!$E$4:$E$78)),0) -> 0 | K9: =IFERROR(SUMPRODUCT((TEXT('💵 Sales'!$B$4:$B$78,"mmm")="Oct")*IF($C$3="",1,('💵 Sales'!$B$4:$B$78<>"")*(YEAR('💵 Sales'!$B$4:$B$78)=$C$3))*IF('💵 Sales'!$E$4:$E$78="",0,'💵 Sales'!$E$4:$E$78)),0) -> 0 | L9: =IFERROR(SUMPRODUCT((TEXT('💵 Sales'!$B$4:$B$78,"mmm")="Nov")*IF($C$3="",1,('💵 Sales'!$B$4:$B$78<>"")*(YEAR('💵 Sales'!$B$4:$B$78)=$C$3))*IF('💵 Sales'!$E$4:$E$78="",0,'💵 Sales'!$E$4:$E$78)),0) -> 0 | M9: =IFERROR(SUMPRODUCT((TEXT('💵 Sales'!$B$4:$B$78,"mmm")="Dec")*IF($C$3="",1,('💵 Sales'!$B$4:$B$78<>"")*(YEAR('💵 Sales'!$B$4:$B$78)=$C$3))*IF('💵 Sales'!$E$4:$E$78="",0,'💵 Sales'!$E$4:$E$78)),0) -> 0 | N9: =SUM(B9:M9) -> 70
A11: 📦 MONTHLY PURCHASES
A12: 🛒 Total Spent on Purchases ($) | B12: =IFERROR(SUMPRODUCT((TEXT('📦 Purchases'!$B$4:$B$78,"mmm")="Jan")*IF($C$3="",1,('📦 Purchases'!$B$4:$B$78<>"")*(YEAR('📦 Purchases'!$B$4:$B$78)=$C$3))*IF('📦 Purchases'!$G$4:$G$78="",0,'📦 Purchases'!$G$4:$G$78)),0) -> 0 | C12: =IFERROR(SUMPRODUCT((TEXT('📦 Purchases'!$B$4:$B$78,"mmm")="Feb")*IF($C$3="",1,('📦 Purchases'!$B$4:$B$78<>"")*(YEAR('📦 Purchases'!$B$4:$B$78)=$C$3))*IF('📦 Purchases'!$G$4:$G$78="",0,'📦 Purchases'!$G$4:$G$78)),0) -> 0 | D12: =IFERROR(SUMPRODUCT((TEXT('📦 Purchases'!$B$4:$B$78,"mmm")="Mar")*IF($C$3="",1,('📦 Purchases'!$B$4:$B$78<>"")*(YEAR('📦 Purchases'!$B$4:$B$78)=$C$3))*IF('📦 Purchases'!$G$4:$G$78="",0,'📦 Purchases'!$G$4:$G$78)),0) -> 0 | E12: =IFERROR(SUMPRODUCT((TEXT('📦 Purchases'!$B$4:$B$78,"mmm")="Apr")*IF($C$3="",1,('📦 Purchases'!$B$4:$B$78<>"")*(YEAR('📦 Purchases'!$B$4:$B$78)=$C$3))*IF('📦 Purchases'!$G$4:$G$78="",0,'📦 Purchases'!$G$4:$G$78)),0) -> 750.11 | F12: =IFERROR(SUMPRODUCT((TEXT('📦 Purchases'!$B$4:$B$78,"mmm")="May")*IF($C$3="",1,('📦 Purchases'!$B$4:$B$78<>"")*(YEAR('📦 Purchases'!$B$4:$B$78)=$C$3))*IF('📦 Purchases'!$G$4:$G$78="",0,'📦 Purchases'!$G$4:$G$78)),0) -> 554.55 | G12: =IFERROR(SUMPRODUCT((TEXT('📦 Purchases'!$B$4:$B$78,"mmm")="Jun")*IF($C$3="",1,('📦 Purchases'!$B$4:$B$78<>"")*(YEAR('📦 Purchases'!$B$4:$B$78)=$C$3))*IF('📦 Purchases'!$G$4:$G$78="",0,'📦 Purchases'!$G$4:$G$78)),0) -> 0 | H12: =IFERROR(SUMPRODUCT((TEXT('📦 Purchases'!$B$4:$B$78,"mmm")="Jul")*IF($C$3="",1,('📦 Purchases'!$B$4:$B$78<>"")*(YEAR('📦 Purchases'!$B$4:$B$78)=$C$3))*IF('📦 Purchases'!$G$4:$G$78="",0,'📦 Purchases'!$G$4:$G$78)),0) -> 0 | I12: =IFERROR(SUMPRODUCT((TEXT('📦 Purchases'!$B$4:$B$78,"mmm")="Aug")*IF($C$3="",1,('📦 Purchases'!$B$4:$B$78<>"")*(YEAR('📦 Purchases'!$B$4:$B$78)=$C$3))*IF('📦 Purchases'!$G$4:$G$78="",0,'📦 Purchases'!$G$4:$G$78)),0) -> 0 | J12: =IFERROR(SUMPRODUCT((TEXT('📦 Purchases'!$B$4:$B$78,"mmm")="Sep")*IF($C$3="",1,('📦 Purchases'!$B$4:$B$78<>"")*(YEAR('📦 Purchases'!$B$4:$B$78)=$C$3))*IF('📦 Purchases'!$G$4:$G$78="",0,'📦 Purchases'!$G$4:$G$78)),0) -> 0 | K12: =IFERROR(SUMPRODUCT((TEXT('📦 Purchases'!$B$4:$B$78,"mmm")="Oct")*IF($C$3="",1,('📦 Purchases'!$B$4:$B$78<>"")*(YEAR('📦 Purchases'!$B$4:$B$78)=$C$3))*IF('📦 Purchases'!$G$4:$G$78="",0,'📦 Purchases'!$G$4:$G$78)),0) -> 0 | L12: =IFERROR(SUMPRODUCT((TEXT('📦 Purchases'!$B$4:$B$78,"mmm")="Nov")*IF($C$3="",1,('📦 Purchases'!$B$4:$B$78<>"")*(YEAR('📦 Purchases'!$B$4:$B$78)=$C$3))*IF('📦 Purchases'!$G$4:$G$78="",0,'📦 Purchases'!$G$4:$G$78)),0) -> 0 | M12: =IFERROR(SUMPRODUCT((TEXT('📦 Purchases'!$B$4:$B$78,"mmm")="Dec")*IF($C$3="",1,('📦 Purchases'!$B$4:$B$78<>"")*(YEAR('📦 Purchases'!$B$4:$B$78)=$C$3))*IF('📦 Purchases'!$G$4:$G$78="",0,'📦 Purchases'!$G$4:$G$78)),0) -> 0 | N12: =SUM(B12:M12) -> 1304.66
A13: 💸 MONTHLY OVERHEAD EXPENSES (Non-Product Costs)
A14: 🧾 Total Overhead Expenses ($) | B14: =IFERROR(SUMPRODUCT((TEXT('💸 Overhead Expenses'!$B$4:$B$78,"mmm")="Jan")*IF($C$3="",1,('💸 Overhead Expenses'!$B$4:$B$78<>"")*(YEAR('💸 Overhead Expenses'!$B$4:$B$78)=$C$3))*IF('💸 Overhead Expenses'!$E$4:$E$78="",0,'💸 Overhead Expenses'!$E$4:$E$78)),0) -> 0 | C14: =IFERROR(SUMPRODUCT((TEXT('💸 Overhead Expenses'!$B$4:$B$78,"mmm")="Feb")*IF($C$3="",1,('💸 Overhead Expenses'!$B$4:$B$78<>"")*(YEAR('💸 Overhead Expenses'!$B$4:$B$78)=$C$3))*IF('💸 Overhead Expenses'!$E$4:$E$78="",0,'💸 Overhead Expenses'!$E$4:$E$78)),0) -> 0 | D14: =IFERROR(SUMPRODUCT((TEXT('💸 Overhead Expenses'!$B$4:$B$78,"mmm")="Mar")*IF($C$3="",1,('💸 Overhead Expenses'!$B$4:$B$78<>"")*(YEAR('💸 Overhead Expenses'!$B$4:$B$78)=$C$3))*IF('💸 Overhead Expenses'!$E$4:$E$78="",0,'💸 Overhead Expenses'!$E$4:$E$78)),0) -> 0 | E14: =IFERROR(SUMPRODUCT((TEXT('💸 Overhead Expenses'!$B$4:$B$78,"mmm")="Apr")*IF($C$3="",1,('💸 Overhead Expenses'!$B$4:$B$78<>"")*(YEAR('💸 Overhead Expenses'!$B$4:$B$78)=$C$3))*IF('💸 Overhead Expenses'!$E$4:$E$78="",0,'💸 Overhead Expenses'!$E$4:$E$78)),0) -> 393.02 | F14: =IFERROR(SUMPRODUCT((TEXT('💸 Overhead Expenses'!$B$4:$B$78,"mmm")="May")*IF($C$3="",1,('💸 Overhead Expenses'!$B$4:$B$78<>"")*(YEAR('💸 Overhead Expenses'!$B$4:$B$78)=$C$3))*IF('💸 Overhead Expenses'!$E$4:$E$78="",0,'💸 Overhead Expenses'!$E$4:$E$78)),0) -> 110 | G14: =IFERROR(SUMPRODUCT((TEXT('💸 Overhead Expenses'!$B$4:$B$78,"mmm")="Jun")*IF($C$3="",1,('💸 Overhead Expenses'!$B$4:$B$78<>"")*(YEAR('💸 Overhead Expenses'!$B$4:$B$78)=$C$3))*IF('💸 Overhead Expenses'!$E$4:$E$78="",0,'💸 Overhead Expenses'!$E$4:$E$78)),0) -> 0 | H14: =IFERROR(SUMPRODUCT((TEXT('💸 Overhead Expenses'!$B$4:$B$78,"mmm")="Jul")*IF($C$3="",1,('💸 Overhead Expenses'!$B$4:$B$78<>"")*(YEAR('💸 Overhead Expenses'!$B$4:$B$78)=$C$3))*IF('💸 Overhead Expenses'!$E$4:$E$78="",0,'💸 Overhead Expenses'!$E$4:$E$78)),0) -> 0 | I14: =IFERROR(SUMPRODUCT((TEXT('💸 Overhead Expenses'!$B$4:$B$78,"mmm")="Aug")*IF($C$3="",1,('💸 Overhead Expenses'!$B$4:$B$78<>"")*(YEAR('💸 Overhead Expenses'!$B$4:$B$78)=$C$3))*IF('💸 Overhead Expenses'!$E$4:$E$78="",0,'💸 Overhead Expenses'!$E$4:$E$78)),0) -> 0 | J14: =IFERROR(SUMPRODUCT((TEXT('💸 Overhead Expenses'!$B$4:$B$78,"mmm")="Sep")*IF($C$3="",1,('💸 Overhead Expenses'!$B$4:$B$78<>"")*(YEAR('💸 Overhead Expenses'!$B$4:$B$78)=$C$3))*IF('💸 Overhead Expenses'!$E$4:$E$78="",0,'💸 Overhead Expenses'!$E$4:$E$78)),0) -> 0 | K14: =IFERROR(SUMPRODUCT((TEXT('💸 Overhead Expenses'!$B$4:$B$78,"mmm")="Oct")*IF($C$3="",1,('💸 Overhead Expenses'!$B$4:$B$78<>"")*(YEAR('💸 Overhead Expenses'!$B$4:$B$78)=$C$3))*IF('💸 Overhead Expenses'!$E$4:$E$78="",0,'💸 Overhead Expenses'!$E$4:$E$78)),0) -> 0 | L14: =IFERROR(SUMPRODUCT((TEXT('💸 Overhead Expenses'!$B$4:$B$78,"mmm")="Nov")*IF($C$3="",1,('💸 Overhead Expenses'!$B$4:$B$78<>"")*(YEAR('💸 Overhead Expenses'!$B$4:$B$78)=$C$3))*IF('💸 Overhead Expenses'!$E$4:$E$78="",0,'💸 Overhead Expenses'!$E$4:$E$78)),0) -> 0 | M14: =IFERROR(SUMPRODUCT((TEXT('💸 Overhead Expenses'!$B$4:$B$78,"mmm")="Dec")*IF($C$3="",1,('💸 Overhead Expenses'!$B$4:$B$78<>"")*(YEAR('💸 Overhead Expenses'!$B$4:$B$78)=$C$3))*IF('💸 Overhead Expenses'!$E$4:$E$78="",0,'💸 Overhead Expenses'!$E$4:$E$78)),0) -> 0 | N14: =SUM(B14:M14) -> 503.02
A15: ✅ True Net (Profit − Overhead) | B15: =B7-B14 -> 0 | C15: =C7-C14 -> 0 | D15: =D7-D14 -> 0 | E15: =E7-E14 -> -34.99 | F15: =F7-F14 -> 402.87 | G15: =G7-G14 -> 0 | H15: =H7-H14 -> 0 | I15: =I7-I14 -> 0 | ... M15: =M7-M14 -> 0 | N15: =SUM(B15:M15) -> 367.88
A16: 💹 Net Cash Flow (Profit − Purchases − Overhead) | B16: =B7-B12-B14 -> 0 | C16: =C7-C12-C14 -> 0 | D16: =D7-D12-D14 -> 0 | E16: =E7-E12-E14 -> -785.1 | F16: =F7-F12-F14 -> -151.68 | G16: =G7-G12-G14 -> 0 | H16: =H7-H12-H14 -> 0 | I16: =I7-I12-I14 -> 0 | ... M16: =M7-M12-M14 -> 0 | N16: =SUM(B16:M16) -> -936.78

Sheet 💸 Overhead Expenses
A1: 💸 OVERHEAD EXPENSES — Non-Product Monthly Costs
A2: Log recurring business costs NOT tied to specific products e.g. platform fees, shipping supplies, storage, ads, tools
A3: # | B3: Date | C3: Expense Name | D3: Category | E3: Amount ($) | F3: Payment Method | G3: Recurring? | H3: Notes
A4: =IF(B4="","",ROW()-3) -> 1 | B4: 46126 | C4: Refract | D4: Bot | E4: 50 | F4: Zelle | G4: Yes
A5: =IF(B5="","",ROW()-3) -> 2 | B5: 46142 | C5: SMS | D5: sms | E5: 97.12 | F5: Business Gold | G5: No
A6: =IF(B6="","",ROW()-3) -> 3 | B6: 46142 | C6: Proxies | D6: Proxy | E6: 172.45 | F6: Business Gold | G6: No | H6: Combined
A7: =IF(B7="","",ROW()-3) -> 4 | B7: 46124 | C7: AYCD | D7: Profile builder | E7: 60 | F7: Business Gold | G7: Yes
A8: =IF(B8="","",ROW()-3) -> 5 | B8: 46140 | C8: Unknown Collectors | D8: Whop/Cord Group | E8: 10.5 | F8: Business Gold | G8: Yes
A9: =IF(B9="","",ROW()-3) -> 6 | B9: 46142 | C9: Flips University | D9: Whop/Cord Group | E9: 2.95 | F9: Business Gold | G9: Yes
A10: =IF(B10="","",ROW()-3) -> 7 | B10: 46156 | C10: Refract | D10: Bot | E10: 50 | F10: Zelle | G10: Yes
A11: =IF(B11="","",ROW()-3) -> 8 | B11: 46156 | C11: Server | D11: Bot | E11: 60 | F11: Zelle/apple pay | G11: Yes
A12: =IF(B12="","",ROW()-3)
A13: =IF(B13="","",ROW()-3)
A14: =IF(B14="","",ROW()-3)
A15: =IF(B15="","",ROW()-3)
A16: =IF(B16="","",ROW()-3)
A17: =IF(B17="","",ROW()-3)
A18: =IF(B18="","",ROW()-3)
A19: =IF(B19="","",ROW()-3)
A20: =IF(B20="","",ROW()-3)
A21: =IF(B21="","",ROW()-3)
A22: =IF(B22="","",ROW()-3)
A23: =IF(B23="","",ROW()-3)
... A78: =IF(B78="","",ROW()-3)
A79: TOTAL OVERHEAD | E79: =SUM(E4:E78) -> 503.02
A81: 💡 Example categories: eBay Fees · PayPal Fees · Shipping Supplies · Bubble Wrap / Boxes · Storage Unit · Printer Ink · Listing Software · Facebook Ads · Gas / Mileage · Phone Bill · Internet · Other
